{
  "slug": "sostoyaniya-komponenta",
  "term": "Состояния компонента",
  "category": "Архитектура",
  "visualType": "interactive",
  "visualNote": "Перебор состояний: default/hover/active/disabled/loading/error",
  "definition": "Визуальные варианты компонента для разных ситуаций: default, hover, active, disabled, loading, error, focus. Полный набор — обязательное требование зрелой ДС.",
  "meta": {
    "usedIn": "Кнопки, поля ввода, чекбоксы, тогглы — любые интерактивные элементы.",
    "relatedTo": []
  },
  "sources": "ОТП (проблема hover в мобильной ДС), Gravity UI, VKUI, Hexa UI",
  "relatedCases": [],
  "relatedTerms": []
}
